.clang-format
.flake8
.gitignore
.gitmodules
CHANGELOG.md
CODEOWNERS
CODE_OF_CONDUCT
Dockerfile
Dockerfile-cuda
Dockerfile-embedded
LICENSE
MANIFEST.in
Makefile
README.md
__init__.py
description.txt
packages.txt
setup.py
./src/opendr/__init__.py
./src/opendr/_setup.py
./src/opendr/_version.py
./src/opendr/control/__init__.py
./src/opendr/engine/__init__.py
./src/opendr/engine/constants.py
./src/opendr/engine/data.py
./src/opendr/engine/datasets.py
./src/opendr/engine/example_learner.py
./src/opendr/engine/learners.py
./src/opendr/engine/target.py
./src/opendr/perception/__init__.py
./src/opendr/perception/fall_detection/__init__.py
./src/opendr/perception/fall_detection/dependencies.ini
./src/opendr/perception/fall_detection/fall_detector_learner.py
./src/opendr/planning/__init__.py
./src/opendr/simulation/__init__.py
./src/opendr/utils/__init__.py
./src/opendr_toolkit_fall_detection.egg-info/PKG-INFO
./src/opendr_toolkit_fall_detection.egg-info/SOURCES.txt
./src/opendr_toolkit_fall_detection.egg-info/dependency_links.txt
./src/opendr_toolkit_fall_detection.egg-info/requires.txt
./src/opendr_toolkit_fall_detection.egg-info/top_level.txt
src/opendr/_setup.py
src/opendr/_version.py
src/opendr/perception/fall_detection/__init__.py
src/opendr/perception/fall_detection/dependencies.ini
src/opendr/perception/fall_detection/fall_detector_learner.py